GeneralTmm/__init__.py
GeneralTmm/_GeneralTMMPy.py
GeneralTmm/_GeneralTmmCpp.py
GeneralTmm/_GeneralTmmCppExt.cpython-37m-x86_64-linux-gnu.so
GeneralTmm/.gitignore
GeneralTmm/src/Layer.cpp
GeneralTmm/src/tmm.h
GeneralTmm/src/Layer.h
GeneralTmm/src/tmm.cpp
GeneralTmm/src/Common.cpp
GeneralTmm/src/CppGeneralTmm.pxd
GeneralTmm/src/GeneralTmm.pyx
GeneralTmm/src/Common.h
GeneralTmm/src/GeneralTmm.cpp
GeneralTmm/src/Material.cpp
GeneralTmm/src/.gitignore
GeneralTmm/src/Material.h
GeneralTmm/src/Simplex/criteria.h
GeneralTmm/src/Simplex/README.txt
GeneralTmm/src/Simplex/state.h
GeneralTmm/src/Simplex/test_rosenbrock_simplex.cpp
GeneralTmm/src/Simplex/simplex.h
GeneralTmm-1.1.1.dist-info/WHEEL
GeneralTmm-1.1.1.dist-info/RECORD
GeneralTmm-1.1.1.dist-info/METADATA
GeneralTmm-1.1.1.dist-info/top_level.txt
