Metadata-Version: 2.1
Name: GeneralTmm
Version: 1.1.1
Summary: General 4x4 transfer-matric method (TMM)
Home-page: https://github.com/ardiloot/GeneralTmm
Author: Ardi Loot
Author-email: ardi.loot@outlook.com
Requires-Python: >=3.5
Requires-Dist: numpy
Requires-Dist: scipy
Requires-Dist: eigency (>=2.0.0)
